<package>
  <description brief="Meta package for kobukibot">

    The meta package for the kobuki stack.
     
  </description>
  <author>Younghun Ju</author>
  <license>Yujin</license>
  <review status="unreviewed" notes=""/>
  <url>http://www.ros.org/wiki/kobuki/kobuki_bringup</url>

  <!-- Kobuki -->
  <depend package="kobuki_node"/>
  <depend package="kobuki_description"/>
 
  <!-- Turtlebot --> 
  <depend package="turtlebot_teleop"/> <!-- launch file dependency -->
  
  <!--  Ros -->
  <depend package="robot_state_publisher"/>

  <!-- visualization -->
  <depend package="rviz"/>
  <depend package="joint_state_publisher"/>
  
  <!-- System Utilities -->
  <rosdep name="unison"/>

  <!-- 3d Sensing -->
  <depend package="openni_camera"/>
  <depend package="pointcloud_to_laserscan"/>

  <!-- Integrate Later
  <depends package="navigation"/>
  <depends package="gmapping"/>
 -->
 
</package>
